Workbook

Sheet Custos Fornecedores
A1: Fornecedor | B1: Modelo | C1: Tamanho | D1: Cor | E1: Gramatura | F1: Preço/Kg (R$) | G1: Peso Milheiro (kg) | H1: Custo Milheiro (R$) | I1: Custo Unitário (R$/un)
A2: Alquimia | B2: Alça Camiseta | C2: 30x40 | D2: Branco/Preto | E2: 0,04-0,06 | F2: 23 | G2: 4.4 | H2: 101.2 | I2: =H2/1000 -> 0.1012
A3: Marfel | B3: Alça Camiseta | C3: 30x40 | D3: Branco/Preto | E3: 0,05 | F3: 31 | G3: 5 | H3: 155 | I3: =H3/1000 -> 0.155
A4: Alquimia | B4: Alça Camiseta | C4: 30x40 | D4: Colorida | E4: 0,06 | F4: 26.5 | G4: 6.2 | H4: 164.3 | I4: =H4/1000 -> 0.1643
A5: Marfel | B5: Alça Camiseta | C5: 30x40 | D5: Colorida | E5: 0,05 | F5: 34.2 | G5: 5 | H5: 171 | I5: =H5/1000 -> 0.171
A6: Alquimia | B6: Alça Camiseta | C6: 40x50 | D6: Branco/Preto | E6: 0,05 | F6: 23 | G6: 9 | H6: 207 | I6: =H6/1000 -> 0.207
A7: Marfel | B7: Alça Camiseta | C7: 40x50 | D7: Branco/Preto | E7: 0,05 | F7: 31 | G7: 9 | H7: 279 | I7: =H7/1000 -> 0.279
A8: Alquimia | B8: Alça Camiseta | C8: 40x50 | D8: Colorida | E8: 0,06 | F8: 26.5 | G8: 11 | H8: 291.5 | I8: =H8/1000 -> 0.2915
A9: Marfel | B9: Alça Camiseta | C9: 40x50 | D9: Colorida | E9: 0,05 | F9: 34.2 | G9: 9 | H9: 307.8 | I9: =H9/1000 -> 0.3078
A10: Alquimia | B10: Alça Camiseta | C10: 45x60 | D10: Branco/Preto | E10: 0,05 | F10: 23 | G10: 12.2 | H10: 280.6 | I10: =H10/1000 -> 0.2806
A11: Marfel | B11: Alça Camiseta | C11: 45x60 | D11: Branco/Preto | E11: 0,05 | F11: 31 | G11: 13.5 | H11: 418.5 | I11: =H11/1000 -> 0.4185
A12: Alquimia | B12: Alça Camiseta | C12: 45x60 | D12: Colorida | E12: 0,06 | F12: 26.5 | G12: 14 | H12: 322 | I12: =H12/1000 -> 0.322
A13: Marfel | B13: Alça Camiseta | C13: 45x60 | D13: Colorida | E13: 0,05 | F13: 34.2 | G13: 13.5 | H13: 461.7 | I13: =H13/1000 -> 0.4617
... A55: Alquimia | B55: Alça Vazada | C55: 50x60 | D55: Colorida (transp.) | E55: 0,10 | F55: 26.5 | G55: 30 | H55: 795 | I55: =H55/1000 -> 0.795
A57: Fonte: FornecedorCusto (banco de dados). Custo Unitário = Custo Milheiro ÷ 1000. Quando um Modelo+Tamanho tem várias cores, usa-se o MAIOR custo entre elas por fornecedor (critério conservador de segurança financeira).

Sheet Auditoria de Preços
A1: AUDITORIA PROFISSIONAL DE TABELA DE PREÇOS — Serigraph e Cia
A2: Regra: sempre o MAIOR custo entre Marfel e Alquimia (nunca média, nunca o menor) · + R$0,30/un de acréscimo operacional aplicado ANTES da margem · margem aplicada por faixa de quantidade (100% → 40%, da menor para a maior)
A4: Produto | B4: Tamanho | C4: Faixa de Quantidade | D4: Qtd. de referência | E4: Valor Marfel (R$/un) | F4: Valor Alquimia (R$/un) | G4: Maior valor utilizado (R$/un) | H4: Fornecedor utilizado | I4: Acréscimo operacional (R$/un) | J4: Acréscimo operacional (R$0,30 × qtd.) | K4: Custo total atualizado (R$/un) | L4: Percentual aplicado | M4: Preço final de venda (R$/un) | N4: Preço atual na tabela (R$/un) | O4: Diferença (Novo − Atual) | P4: Observações
A5: Alça Camiseta | B5: 30x40 | C5: 100–199 | D5: 100 | E5: =IFERROR(_xlfn.MAXIFS('Custos Fornecedores'!$I$2:$I$55,'Custos Fornecedores'!$B$2:$B$55,$A5,'Custos Fornecedores'!$C$2:$C$55,$B5,'Custos Fornecedores'!$A$2:$A$55,"Marfel"),0) -> 0.171 | F5: =IFERROR(_xlfn.MAXIFS('Custos Fornecedores'!$I$2:$I$55,'Custos Fornecedores'!$B$2:$B$55,$A5,'Custos Fornecedores'!$C$2:$C$55,$B5,'Custos Fornecedores'!$A$2:$A$55,"Alquimia"),0) -> 0.1643 | G5: =IF(E5=0,F5,IF(F5=0,E5,MAX(E5,F5))) -> 0.171 | H5: =IF(AND(E5=0,F5=0),"SEM DADOS",IF(E5=0,"Alquimia (único)",IF(F5=0,"Marfel (único)",IF(E5>=F5,"Marfel","Alquimia")))) -> Marfel | I5: 0.3 | J5: =I5*D5 -> 30 | K5: =G5+I5 -> 0.471 | L5: 1 | M5: =K5*(1+L5) -> 0.942 | N5: 0.91 | O5: =M5-N5 -> 0.032 | P5: =IF(ISNUMBER(SEARCH("único",H5)),"Custo disponível de apenas 1 fornecedor para este tamanho — ver aba Inconsistências.","")
A6: Alça Camiseta | B6: 30x40 | C6: 200–299 | D6: 200 | E6: =IFERROR(_xlfn.MAXIFS('Custos Fornecedores'!$I$2:$I$55,'Custos Fornecedores'!$B$2:$B$55,$A6,'Custos Fornecedores'!$C$2:$C$55,$B6,'Custos Fornecedores'!$A$2:$A$55,"Marfel"),0) -> 0.171 | F6: =IFERROR(_xlfn.MAXIFS('Custos Fornecedores'!$I$2:$I$55,'Custos Fornecedores'!$B$2:$B$55,$A6,'Custos Fornecedores'!$C$2:$C$55,$B6,'Custos Fornecedores'!$A$2:$A$55,"Alquimia"),0) -> 0.1643 | G6: =IF(E6=0,F6,IF(F6=0,E6,MAX(E6,F6))) -> 0.171 | H6: =IF(AND(E6=0,F6=0),"SEM DADOS",IF(E6=0,"Alquimia (único)",IF(F6=0,"Marfel (único)",IF(E6>=F6,"Marfel","Alquimia")))) -> Marfel | I6: 0.3 | J6: =I6*D6 -> 60 | K6: =G6+I6 -> 0.471 | L6: 0.75 | M6: =K6*(1+L6) -> 0.82425 | N6: 0.8 | O6: =M6-N6 -> 0.02425 | P6: =IF(ISNUMBER(SEARCH("único",H6)),"Custo disponível de apenas 1 fornecedor para este tamanho — ver aba Inconsistências.","")
A7: Alça Camiseta | B7: 30x40 | C7: 300–399 | D7: 300 | E7: =IFERROR(_xlfn.MAXIFS('Custos Fornecedores'!$I$2:$I$55,'Custos Fornecedores'!$B$2:$B$55,$A7,'Custos Fornecedores'!$C$2:$C$55,$B7,'Custos Fornecedores'!$A$2:$A$55,"Marfel"),0) -> 0.171 | F7: =IFERROR(_xlfn.MAXIFS('Custos Fornecedores'!$I$2:$I$55,'Custos Fornecedores'!$B$2:$B$55,$A7,'Custos Fornecedores'!$C$2:$C$55,$B7,'Custos Fornecedores'!$A$2:$A$55,"Alquimia"),0) -> 0.1643 | G7: =IF(E7=0,F7,IF(F7=0,E7,MAX(E7,F7))) -> 0.171 | H7: =IF(AND(E7=0,F7=0),"SEM DADOS",IF(E7=0,"Alquimia (único)",IF(F7=0,"Marfel (único)",IF(E7>=F7,"Marfel","Alquimia")))) -> Marfel | I7: 0.3 | J7: =I7*D7 -> 90 | K7: =G7+I7 -> 0.471 | L7: 0.7 | M7: =K7*(1+L7) -> 0.8007 | N7: 0.77 | O7: =M7-N7 -> 0.0307 | P7: =IF(ISNUMBER(SEARCH("único",H7)),"Custo disponível de apenas 1 fornecedor para este tamanho — ver aba Inconsistências.","")
A8: Alça Camiseta | B8: 30x40 | C8: 400–499 | D8: 400 | E8: =IFERROR(_xlfn.MAXIFS('Custos Fornecedores'!$I$2:$I$55,'Custos Fornecedores'!$B$2:$B$55,$A8,'Custos Fornecedores'!$C$2:$C$55,$B8,'Custos Fornecedores'!$A$2:$A$55,"Marfel"),0) -> 0.171 | F8: =IFERROR(_xlfn.MAXIFS('Custos Fornecedores'!$I$2:$I$55,'Custos Fornecedores'!$B$2:$B$55,$A8,'Custos Fornecedores'!$C$2:$C$55,$B8,'Custos Fornecedores'!$A$2:$A$55,"Alquimia"),0) -> 0.1643 | G8: =IF(E8=0,F8,IF(F8=0,E8,MAX(E8,F8))) -> 0.171 | H8: =IF(AND(E8=0,F8=0),"SEM DADOS",IF(E8=0,"Alquimia (único)",IF(F8=0,"Marfel (único)",IF(E8>=F8,"Marfel","Alquimia")))) -> Marfel | I8: 0.3 | J8: =I8*D8 -> 120 | K8: =G8+I8 -> 0.471 | L8: 0.65 | M8: =K8*(1+L8) -> 0.77715 | N8: 0.75 | O8: =M8-N8 -> 0.02715 | P8: =IF(ISNUMBER(SEARCH("único",H8)),"Custo disponível de apenas 1 fornecedor para este tamanho — ver aba Inconsistências.","")
A9: Alça Camiseta | B9: 30x40 | C9: 500–599 | D9: 500 | E9: =IFERROR(_xlfn.MAXIFS('Custos Fornecedores'!$I$2:$I$55,'Custos Fornecedores'!$B$2:$B$55,$A9,'Custos Fornecedores'!$C$2:$C$55,$B9,'Custos Fornecedores'!$A$2:$A$55,"Marfel"),0) -> 0.171 | F9: =IFERROR(_xlfn.MAXIFS('Custos Fornecedores'!$I$2:$I$55,'Custos Fornecedores'!$B$2:$B$55,$A9,'Custos Fornecedores'!$C$2:$C$55,$B9,'Custos Fornecedores'!$A$2:$A$55,"Alquimia"),0) -> 0.1643 | G9: =IF(E9=0,F9,IF(F9=0,E9,MAX(E9,F9))) -> 0.171 | H9: =IF(AND(E9=0,F9=0),"SEM DADOS",IF(E9=0,"Alquimia (único)",IF(F9=0,"Marfel (único)",IF(E9>=F9,"Marfel","Alquimia")))) -> Marfel | I9: 0.3 | J9: =I9*D9 -> 150 | K9: =G9+I9 -> 0.471 | L9: 0.6 | M9: =K9*(1+L9) -> 0.7536 | N9: 0.73 | O9: =M9-N9 -> 0.0236 | P9: =IF(ISNUMBER(SEARCH("único",H9)),"Custo disponível de apenas 1 fornecedor para este tamanho — ver aba Inconsistências.","")
A10: Alça Camiseta | B10: 30x40 | C10: 600–699 | D10: 600 | E10: =IFERROR(_xlfn.MAXIFS('Custos Fornecedores'!$I$2:$I$55,'Custos Fornecedores'!$B$2:$B$55,$A10,'Custos Fornecedores'!$C$2:$C$55,$B10,'Custos Fornecedores'!$A$2:$A$55,"Marfel"),0) -> 0.171 | F10: =IFERROR(_xlfn.MAXIFS('Custos Fornecedores'!$I$2:$I$55,'Custos Fornecedores'!$B$2:$B$55,$A10,'Custos Fornecedores'!$C$2:$C$55,$B10,'Custos Fornecedores'!$A$2:$A$55,"Alquimia"),0) -> 0.1643 | G10: =IF(E10=0,F10,IF(F10=0,E10,MAX(E10,F10))) -> 0.171 | H10: =IF(AND(E10=0,F10=0),"SEM DADOS",IF(E10=0,"Alquimia (único)",IF(F10=0,"Marfel (único)",IF(E10>=F10,"Marfel","Alquimia")))) -> Marfel | I10: 0.3 | J10: =I10*D10 -> 180 | K10: =G10+I10 -> 0.471 | L10: 0.57 | M10: =K10*(1+L10) -> 0.73947 | N10: 0.71 | O10: =M10-N10 -> 0.02947 | P10: =IF(ISNUMBER(SEARCH("único",H10)),"Custo disponível de apenas 1 fornecedor para este tamanho — ver aba Inconsistências.","")
A11: Alça Camiseta | B11: 30x40 | C11: 700–799 | D11: 700 | E11: =IFERROR(_xlfn.MAXIFS('Custos Fornecedores'!$I$2:$I$55,'Custos Fornecedores'!$B$2:$B$55,$A11,'Custos Fornecedores'!$C$2:$C$55,$B11,'Custos Fornecedores'!$A$2:$A$55,"Marfel"),0) -> 0.171 | F11: =IFERROR(_xlfn.MAXIFS('Custos Fornecedores'!$I$2:$I$55,'Custos Fornecedores'!$B$2:$B$55,$A11,'Custos Fornecedores'!$C$2:$C$55,$B11,'Custos Fornecedores'!$A$2:$A$55,"Alquimia"),0) -> 0.1643 | G11: =IF(E11=0,F11,IF(F11=0,E11,MAX(E11,F11))) -> 0.171 | H11: =IF(AND(E11=0,F11=0),"SEM DADOS",IF(E11=0,"Alquimia (único)",IF(F11=0,"Marfel (único)",IF(E11>=F11,"Marfel","Alquimia")))) -> Marfel | I11: 0.3 | J11: =I11*D11 -> 210 | K11: =G11+I11 -> 0.471 | L11: 0.54 | M11: =K11*(1+L11) -> 0.72534 | N11: 0.7 | O11: =M11-N11 -> 0.02534 | P11: =IF(ISNUMBER(SEARCH("único",H11)),"Custo disponível de apenas 1 fornecedor para este tamanho — ver aba Inconsistências.","")
A12: Alça Camiseta | B12: 30x40 | C12: 800–899 | D12: 800 | E12: =IFERROR(_xlfn.MAXIFS('Custos Fornecedores'!$I$2:$I$55,'Custos Fornecedores'!$B$2:$B$55,$A12,'Custos Fornecedores'!$C$2:$C$55,$B12,'Custos Fornecedores'!$A$2:$A$55,"Marfel"),0) -> 0.171 | F12: =IFERROR(_xlfn.MAXIFS('Custos Fornecedores'!$I$2:$I$55,'Custos Fornecedores'!$B$2:$B$55,$A12,'Custos Fornecedores'!$C$2:$C$55,$B12,'Custos Fornecedores'!$A$2:$A$55,"Alquimia"),0) -> 0.1643 | G12: =IF(E12=0,F12,IF(F12=0,E12,MAX(E12,F12))) -> 0.171 | H12: =IF(AND(E12=0,F12=0),"SEM DADOS",IF(E12=0,"Alquimia (único)",IF(F12=0,"Marfel (único)",IF(E12>=F12,"Marfel","Alquimia")))) -> Marfel | I12: 0.3 | J12: =I12*D12 -> 240 | K12: =G12+I12 -> 0.471 | L12: 0.51 | M12: =K12*(1+L12) -> 0.71121 | N12: 0.69 | O12: =M12-N12 -> 0.02121 | P12: =IF(ISNUMBER(SEARCH("único",H12)),"Custo disponível de apenas 1 fornecedor para este tamanho — ver aba Inconsistências.","")
A13: Alça Camiseta | B13: 30x40 | C13: 900–999 | D13: 900 | E13: =IFERROR(_xlfn.MAXIFS('Custos Fornecedores'!$I$2:$I$55,'Custos Fornecedores'!$B$2:$B$55,$A13,'Custos Fornecedores'!$C$2:$C$55,$B13,'Custos Fornecedores'!$A$2:$A$55,"Marfel"),0) -> 0.171 | F13: =IFERROR(_xlfn.MAXIFS('Custos Fornecedores'!$I$2:$I$55,'Custos Fornecedores'!$B$2:$B$55,$A13,'Custos Fornecedores'!$C$2:$C$55,$B13,'Custos Fornecedores'!$A$2:$A$55,"Alquimia"),0) -> 0.1643 | G13: =IF(E13=0,F13,IF(F13=0,E13,MAX(E13,F13))) -> 0.171 | H13: =IF(AND(E13=0,F13=0),"SEM DADOS",IF(E13=0,"Alquimia (único)",IF(F13=0,"Marfel (único)",IF(E13>=F13,"Marfel","Alquimia")))) -> Marfel | I13: 0.3 | J13: =I13*D13 -> 270 | K13: =G13+I13 -> 0.471 | L13: 0.48 | M13: =K13*(1+L13) -> 0.69708 | N13: 0.67 | O13: =M13-N13 -> 0.02708 | P13: =IF(ISNUMBER(SEARCH("único",H13)),"Custo disponível de apenas 1 fornecedor para este tamanho — ver aba Inconsistências.","")
A14: Alça Camiseta | B14: 30x40 | C14: 1000+ | D14: 1000 | E14: =IFERROR(_xlfn.MAXIFS('Custos Fornecedores'!$I$2:$I$55,'Custos Fornecedores'!$B$2:$B$55,$A14,'Custos Fornecedores'!$C$2:$C$55,$B14,'Custos Fornecedores'!$A$2:$A$55,"Marfel"),0) -> 0.171 | F14: =IFERROR(_xlfn.MAXIFS('Custos Fornecedores'!$I$2:$I$55,'Custos Fornecedores'!$B$2:$B$55,$A14,'Custos Fornecedores'!$C$2:$C$55,$B14,'Custos Fornecedores'!$A$2:$A$55,"Alquimia"),0) -> 0.1643 | G14: =IF(E14=0,F14,IF(F14=0,E14,MAX(E14,F14))) -> 0.171 | H14: =IF(AND(E14=0,F14=0),"SEM DADOS",IF(E14=0,"Alquimia (único)",IF(F14=0,"Marfel (único)",IF(E14>=F14,"Marfel","Alquimia")))) -> Marfel | I14: 0.3 | J14: =I14*D14 -> 300 | K14: =G14+I14 -> 0.471 | L14: 0.4 | M14: =K14*(1+L14) -> 0.6594 | N14: 0.64 | O14: =M14-N14 -> 0.0194 | P14: =IF(ISNUMBER(SEARCH("único",H14)),"Custo disponível de apenas 1 fornecedor para este tamanho — ver aba Inconsistências.","")
A15: Alça Camiseta | B15: 40x50 | C15: 100–199 | D15: 100 | E15: =IFERROR(_xlfn.MAXIFS('Custos Fornecedores'!$I$2:$I$55,'Custos Fornecedores'!$B$2:$B$55,$A15,'Custos Fornecedores'!$C$2:$C$55,$B15,'Custos Fornecedores'!$A$2:$A$55,"Marfel"),0) -> 0.3078 | F15: =IFERROR(_xlfn.MAXIFS('Custos Fornecedores'!$I$2:$I$55,'Custos Fornecedores'!$B$2:$B$55,$A15,'Custos Fornecedores'!$C$2:$C$55,$B15,'Custos Fornecedores'!$A$2:$A$55,"Alquimia"),0) -> 0.2915 | G15: =IF(E15=0,F15,IF(F15=0,E15,MAX(E15,F15))) -> 0.3078 | H15: =IF(AND(E15=0,F15=0),"SEM DADOS",IF(E15=0,"Alquimia (único)",IF(F15=0,"Marfel (único)",IF(E15>=F15,"Marfel","Alquimia")))) -> Marfel | I15: 0.3 | J15: =I15*D15 -> 30 | K15: =G15+I15 -> 0.6078 | L15: 1 | M15: =K15*(1+L15) -> 1.2156 | N15: 1.16 | O15: =M15-N15 -> 0.0556 | P15: =IF(ISNUMBER(SEARCH("único",H15)),"Custo disponível de apenas 1 fornecedor para este tamanho — ver aba Inconsistências.","")
A16: Alça Camiseta | B16: 40x50 | C16: 200–299 | D16: 200 | E16: =IFERROR(_xlfn.MAXIFS('Custos Fornecedores'!$I$2:$I$55,'Custos Fornecedores'!$B$2:$B$55,$A16,'Custos Fornecedores'!$C$2:$C$55,$B16,'Custos Fornecedores'!$A$2:$A$55,"Marfel"),0) -> 0.3078 | F16: =IFERROR(_xlfn.MAXIFS('Custos Fornecedores'!$I$2:$I$55,'Custos Fornecedores'!$B$2:$B$55,$A16,'Custos Fornecedores'!$C$2:$C$55,$B16,'Custos Fornecedores'!$A$2:$A$55,"Alquimia"),0) -> 0.2915 | G16: =IF(E16=0,F16,IF(F16=0,E16,MAX(E16,F16))) -> 0.3078 | H16: =IF(AND(E16=0,F16=0),"SEM DADOS",IF(E16=0,"Alquimia (único)",IF(F16=0,"Marfel (único)",IF(E16>=F16,"Marfel","Alquimia")))) -> Marfel | I16: 0.3 | J16: =I16*D16 -> 60 | K16: =G16+I16 -> 0.6078 | L16: 0.75 | M16: =K16*(1+L16) -> 1.06365 | N16: 1.01 | O16: =M16-N16 -> 0.05365 | P16: =IF(ISNUMBER(SEARCH("único",H16)),"Custo disponível de apenas 1 fornecedor para este tamanho — ver aba Inconsistências.","")
... A154: Alça Vazada | B154: 50x60 | C154: 1000+ | D154: 1000 | E154: =IFERROR(_xlfn.MAXIFS('Custos Fornecedores'!$I$2:$I$55,'Custos Fornecedores'!$B$2:$B$55,$A154,'Custos Fornecedores'!$C$2:$C$55,$B154,'Custos Fornecedores'!$A$2:$A$55,"Marfel"),0) -> 0 | F154: =IFERROR(_xlfn.MAXIFS('Custos Fornecedores'!$I$2:$I$55,'Custos Fornecedores'!$B$2:$B$55,$A154,'Custos Fornecedores'!$C$2:$C$55,$B154,'Custos Fornecedores'!$A$2:$A$55,"Alquimia"),0) -> 0.795 | G154: =IF(E154=0,F154,IF(F154=0,E154,MAX(E154,F154))) -> 0.795 | H154: =IF(AND(E154=0,F154=0),"SEM DADOS",IF(E154=0,"Alquimia (único)",IF(F154=0,"Marfel (único)",IF(E154>=F154,"Marfel","Alquimia")))) -> Alquimia (único) | I154: 0.3 | J154: =I154*D154 -> 300 | K154: =G154+I154 -> 1.095 | L154: 0.4 | M154: =K154*(1+L154) -> 1.533 | N154: 1.48 | O154: =M154-N154 -> 0.053 | P154: =IF(ISNUMBER(SEARCH("único",H154)),"Custo disponível de apenas 1 fornecedor para este tamanho — ver aba Inconsistências.","") -> Custo disponível de apenas 1 fornecedor para este tamanho — ver aba Inconsistências.

Sheet Inconsistências
A1: INCONSISTÊNCIAS IDENTIFICADAS NA AUDITORIA
A3: Produto / Tema | B3: Descrição da inconsistência e recomendação
A4: Alça Vazada 45x60 | B4: Custo cadastrado apenas para a Marfel (nenhum registro de custo da Alquimia para este tamanho). O 'maior valor' usado nesta faixa é, na prática, o único valor disponível — não há comparação real entre fornecedores. Recomenda-se cadastrar o custo da Alquimia para este tamanho assim que possível.
A5: Alça Vazada 50x60 | B5: Custo cadastrado apenas para a Alquimia (nenhum registro de custo da Marfel para este tamanho). Mesma situação do item acima, em sentido inverso — recomenda-se cadastrar o custo da Marfel.
A6: Taxonomia de cores | B6: Marfel e Alquimia usam nomes de cor diferentes para o mesmo produto (ex.: uma cadastra 'Branco/Preto', outra pode cadastrar por tonalidade individual). Para não subestimar o custo, a auditoria usa o MAIOR custo entre TODAS as cores cadastradas de cada fornecedor, por Modelo+Tamanho — e não uma cor específica. Isso é intencionalmente conservador: garante que nenhum custo real fique de fora do cálculo.
A8: Resultado da revisão financeira (ETAPA 6)
A9: ✔ Maior custo entre Marfel e Alquimia usado em 100% das 150 linhas (nunca média, nunca o menor).
A10: ✔ Acréscimo operacional de R$0,30/unidade aplicado em 100% das linhas, antes da margem.
A11: ✔ Margem aplicada somente sobre (custo + acréscimo), nunca sobre o custo puro.
A12: ✔ Os 10 percentuais fixos (100/75/70/65/60/57/54/51/48/40%) aplicados na ordem correta, da menor para a maior faixa de quantidade, em todos os 15 produtos.
A13: ✔ Nenhuma linha ficou com preço final abaixo do custo total (nenhum risco de prejuízo identificado nos preços propostos).
A14: ⚠ 20 das 150 linhas (2 produtos: Alça Vazada 45x60 e 50x60) têm custo de apenas 1 fornecedor — sinalizadas em amarelo na aba 'Auditoria de Preços' e detalhadas acima.
A15: ✔ Todos os valores arredondados em 2 casas decimais na exibição; cálculo interno mantém precisão total via fórmulas do Excel.
